monobloco/.gitkeep
monobloco/__init__.py
monobloco/main.py
monobloco-0.0.1.dist-info/LICENSE
monobloco-0.0.1.dist-info/WHEEL
monobloco-0.0.1.dist-info/METADATA
monobloco-0.0.1.dist-info/RECORD
