Metadata-Version: 2.1
Name: monobloco
Version: 0.0.1
Summary: Minimalist interfaces for taca taca toco toco taca taca
Author: don toco
Requires-Python: >=3.7,<4.0
Classifier: Programming Language :: Python :: 3
Classifier: Programming Language :: Python :: 3.10
Classifier: Programming Language :: Python :: 3.7
Classifier: Programming Language :: Python :: 3.8
Classifier: Programming Language :: Python :: 3.9
Requires-Dist: numpy (>=1.15,<2.0)
Requires-Dist: tqdm (>=4.40.0,<5.0.0)
